meatie/__init__.py
meatie/aio/__init__.py
meatie/aio/client.py
meatie/aio/descriptor.py
meatie/api_reference.py
meatie/client.py
meatie/descriptor.py
meatie/endpoint.py
meatie/error.py
meatie/internal/adapter/__init__.py
meatie/internal/adapter/bytes_.py
meatie/internal/adapter/client_response.py
meatie/internal/adapter/factory.py
meatie/internal/adapter/json_.py
meatie/internal/adapter/none_.py
meatie/internal/adapter/pydantic_v1.py
meatie/internal/adapter/pydantic_v2.py
meatie/internal/adapter/string_.py
meatie/internal/adapter/types.py
meatie/internal/cache.py
meatie/internal/limit/__init__.py
meatie/internal/limit/limiter.py
meatie/internal/limit/rate.py
meatie/internal/limit/reservation.py
meatie/internal/retry/__init__.py
meatie/internal/retry/condition.py
meatie/internal/retry/context.py
meatie/internal/retry/retry.py
meatie/internal/retry/stop.py
meatie/internal/retry/wait.py
meatie/internal/template/__init__.py
meatie/internal/template/method.py
meatie/internal/template/parameter.py
meatie/internal/template/path.py
meatie/internal/template/request.py
meatie/internal/template/unwrap.py
meatie/internal/types.py
meatie/option/__init__.py
meatie/option/body_option.py
meatie/option/cache_option.py
meatie/option/limit_option.py
meatie/option/private_option.py
meatie/option/retry_option.py
meatie/py.typed
meatie/types.py
meatie_aiohttp/__init__.py
meatie_aiohttp/client.py
meatie_aiohttp/py.typed
meatie_aiohttp/response.py
meatie_httpx/__init__.py
meatie_httpx/async_client.py
meatie_httpx/async_response.py
meatie_httpx/client.py
meatie_httpx/py.typed
meatie_httpx/response.py
meatie_requests/__init__.py
meatie_requests/client.py
meatie_requests/py.typed
meatie_requests/response.py
meatie-0.1.28.dist-info/licenses/LICENSE.md
meatie-0.1.28.dist-info/WHEEL
meatie-0.1.28.dist-info/METADATA
meatie-0.1.28.dist-info/RECORD
