Metadata-Version: 2.4
Name: meatie
Version: 0.1.28
Summary: Meatie is a Python typed REST client library that eliminates the need for boilerplate code when integrating with external APIs. The library generates code for calling a REST API based on method signatures annotated with type hints. Meatie abstracts away mechanics related to HTTP communication, such as building URLs, encoding query parameters, parsing, and dumping Pydantic models. With some modest additional configuration effort, generated HTTP clients offer rate limiting, retries, and c
Keywords: aiohttp,API,api-client,asyncio,HTTP,http-client,httpx,pydantic,requests,REST,type-hints
Author: pmateusz
Author-email: pmateusz <pmateusz@users.noreply.github.com>
License-Expression: BSD-3-Clause
License-File: LICENSE.md
Classifier: Programming Language :: Python :: 3 :: Only
Classifier: Programming Language :: Python :: 3.9
Classifier: Programming Language :: Python :: 3.10
Classifier: Programming Language :: Python :: 3.11
Classifier: Programming Language :: Python :: 3.12
Classifier: Programming Language :: Python :: 3.13
Classifier: Programming Language :: Python :: 3.14
Requires-Dist: typing-extensions>=4.7.0
Requires-Dist: aiohttp>=3.7 ; extra == 'aiohttp'
Requires-Dist: httpx>=0.19 ; extra == 'httpx'
Requires-Dist: pydantic>=1.10 ; extra == 'pydantic'
Requires-Dist: requests>=2.26 ; extra == 'requests'
Requires-Python: >=3.9
Provides-Extra: aiohttp
Provides-Extra: httpx
Provides-Extra: pydantic
Provides-Extra: requests
